{
    "d8c210c4-dd59-ea74-eff6-d7cf1c69465b": {
        "paletteKey": "FlexLayoutCol",
        "designerReference": [
            {
                "_key": "componentLabel",
                "_value": "Column",
                "_type": "kv",
                "_attrDef": "p",
                "_useAsLabel": true
            },
            {
                "_key": "style",
                "_value": "",
                "_type": "kv",
                "_attrDef": "p"
            },
            {
                "_key": "class",
                "_value": "",
                "_type": "kv",
                "_attrDef": "p"
            },
            {
                "_key": "fxFlex",
                "_value": "",
                "_type": "kv",
                "_attrDef": "p"
            },
            {
                "_key": "fxLayoutGap",
                "_value": "",
                "_type": "kv",
                "_attrDef": "p"
            },
            {
                "_key": "wrap",
                "_value": "wrap",
                "_type": "a",
                "_attrDef": "p"
            },
            {
                "_key": "layoutAlign",
                "_value": "center",
                "_type": "a",
                "_attrDef": "p"
            },
            {
                "_key": "pLayoutAlign",
                "_value": "center",
                "_type": "a",
                "_attrDef": "p"
            },
            {
                "_key": "fxShow",
                "_value": "true",
                "_type": "kv",
                "_attrDef": "p"
            },
            {
                "_key": "fxHide",
                "_value": "false",
                "_type": "kv",
                "_attrDef": "p"
            }
        ],
        "604acac2-8471-0964-66df-242746fb0ed5": {
            "paletteKey": "NG-Form",
            "parentEditorKey": "d8c210c4-dd59-ea74-eff6-d7cf1c69465b",
            "designerReference": [
                {
                    "_key": "componentLabel",
                    "_value": "Form",
                    "_type": "kv",
                    "_attrDef": "p",
                    "_useAsLabel": true
                },
                {
                    "_key": "style",
                    "_value": "",
                    "_type": "kv",
                    "_attrDef": "p"
                },
                {
                    "_key": "class",
                    "_value": "",
                    "_type": "kv",
                    "_attrDef": "p"
                },
                {
                    "_key": "action",
                    "_value": "",
                    "_type": "kv",
                    "_attrDef": "p"
                },
                {
                    "_key": "method",
                    "_value": "",
                    "_type": "kv",
                    "_attrDef": "p"
                },
                {
                    "_key": "target",
                    "_value": "",
                    "_type": "kv",
                    "_attrDef": "p"
                },
                {
                    "_key": "(onsubmit)",
                    "_value": "",
                    "_type": "kv",
                    "_attrDef": "p"
                },
                {
                    "_key": "(onreset)",
                    "_value": "",
                    "_type": "kv",
                    "_attrDef": "p"
                }
            ],
            "4c8b1310-d056-9ce1-10ff-e25d636ddd01": {
                "paletteKey": "FlexLayoutRow",
                "parentEditorKey": "604acac2-8471-0964-66df-242746fb0ed5",
                "designerReference": [
                    {
                        "_key": "componentLabel",
                        "_value": "Row",
                        "_type": "kv",
                        "_attrDef": "p",
                        "_useAsLabel": true
                    },
                    {
                        "_key": "style",
                        "_value": "",
                        "_type": "kv",
                        "_attrDef": "p"
                    },
                    {
                        "_key": "class",
                        "_value": "",
                        "_type": "kv",
                        "_attrDef": "p"
                    },
                    {
                        "_key": "fxFlex",
                        "_value": "",
                        "_type": "kv",
                        "_attrDef": "p"
                    },
                    {
                        "_key": "fxLayoutGap",
                        "_value": "20px",
                        "_type": "kv",
                        "_attrDef": "p"
                    },
                    {
                        "_key": "wrap",
                        "_value": "wrap",
                        "_type": "a",
                        "_attrDef": "p"
                    },
                    {
                        "_key": "layoutAlign",
                        "_value": "center",
                        "_type": "a",
                        "_attrDef": "p"
                    },
                    {
                        "_key": "pLayoutAlign",
                        "_value": "center",
                        "_type": "a",
                        "_attrDef": "p"
                    },
                    {
                        "_key": "fxShow",
                        "_value": "true",
                        "_type": "kv",
                        "_attrDef": "p"
                    },
                    {
                        "_key": "fxHide",
                        "_value": "false",
                        "_type": "kv",
                        "_attrDef": "p"
                    }
                ],
                "9e5b7e36-58d7-a2bf-d79d-2ea2096fd400": {
                    "paletteKey": "FlexLayoutCol",
                    "parentEditorKey": "4c8b1310-d056-9ce1-10ff-e25d636ddd01",
                    "designerReference": [
                        {
                            "_key": "componentLabel",
                            "_value": "Column",
                            "_type": "kv",
                            "_attrDef": "p",
                            "_useAsLabel": true
                        },
                        {
                            "_key": "style",
                            "_value": "",
                            "_type": "kv",
                            "_attrDef": "p"
                        },
                        {
                            "_key": "class",
                            "_value": "",
                            "_type": "kv",
                            "_attrDef": "p"
                        },
                        {
                            "_key": "fxFlex",
                            "_value": "",
                            "_type": "kv",
                            "_attrDef": "p"
                        },
                        {
                            "_key": "fxLayoutGap",
                            "_value": "",
                            "_type": "kv",
                            "_attrDef": "p"
                        },
                        {
                            "_key": "wrap",
                            "_value": "wrap",
                            "_type": "a",
                            "_attrDef": "p"
                        },
                        {
                            "_key": "layoutAlign",
                            "_value": "center",
                            "_type": "a",
                            "_attrDef": "p"
                        },
                        {
                            "_key": "pLayoutAlign",
                            "_value": "center",
                            "_type": "a",
                            "_attrDef": "p"
                        },
                        {
                            "_key": "fxShow",
                            "_value": "true",
                            "_type": "kv",
                            "_attrDef": "p"
                        },
                        {
                            "_key": "fxHide",
                            "_value": "false",
                            "_type": "kv",
                            "_attrDef": "p"
                        }
                    ],
                    "21fcd2a8-abac-53de-5f1a-eff23111af7f": {
                        "paletteKey": "FlexLayoutRow",
                        "parentEditorKey": "9e5b7e36-58d7-a2bf-d79d-2ea2096fd400",
                        "designerReference": [
                            {
                                "_key": "componentLabel",
                                "_value": "Row",
                                "_type": "kv",
                                "_attrDef": "p",
                                "_useAsLabel": true
                            },
                            {
                                "_key": "style",
                                "_value": "",
                                "_type": "kv",
                                "_attrDef": "p"
                            },
                            {
                                "_key": "class",
                                "_value": "",
                                "_type": "kv",
                                "_attrDef": "p"
                            },
                            {
                                "_key": "fxFlex",
                                "_value": "",
                                "_type": "kv",
                                "_attrDef": "p"
                            },
                            {
                                "_key": "fxLayoutGap",
                                "_value": "10px",
                                "_type": "kv",
                                "_attrDef": "p"
                            },
                            {
                                "_key": "wrap",
                                "_value": "wrap",
                                "_type": "a",
                                "_attrDef": "p"
                            },
                            {
                                "_key": "layoutAlign",
                                "_value": "center",
                                "_type": "a",
                                "_attrDef": "p"
                            },
                            {
                                "_key": "pLayoutAlign",
                                "_value": "center",
                                "_type": "a",
                                "_attrDef": "p"
                            },
                            {
                                "_key": "fxShow",
                                "_value": "true",
                                "_type": "kv",
                                "_attrDef": "p"
                            },
                            {
                                "_key": "fxHide",
                                "_value": "false",
                                "_type": "kv",
                                "_attrDef": "p"
                            }
                        ],
                        "68ddbba0-7d5d-f084-8803-858696e3ed26": {
                            "paletteKey": "NG-Paragraph",
                            "parentEditorKey": "21fcd2a8-abac-53de-5f1a-eff23111af7f",
                            "designerReference": [
                                {
                                    "_key": "style",
                                    "_value": "",
                                    "_type": "kv",
                                    "_attrDef": "p"
                                },
                                {
                                    "_key": "class",
                                    "_value": "",
                                    "_type": "kv",
                                    "_attrDef": "p"
                                },
                                {
                                    "_key": "text",
                                    "_value": "Risk Title",
                                    "_type": "a",
                                    "_attrDef": "p",
                                    "_useAsLabel": true
                                },
                                {
                                    "_key": "align",
                                    "_value": "",
                                    "_type": "kv",
                                    "_attrDef": "p"
                                }
                            ]
                        },
                        "d578c834-4547-c810-48df-1158e3369472": {
                            "paletteKey": "NG-Input",
                            "parentEditorKey": "21fcd2a8-abac-53de-5f1a-eff23111af7f",
                            "isAdvancedComponent": true,
                            "designerReference": [
                                {
                                    "_key": "style",
                                    "_value": "",
                                    "_type": "kv",
                                    "_attrDef": "p"
                                },
                                {
                                    "_key": "class",
                                    "_value": "",
                                    "_type": "kv",
                                    "_attrDef": "p"
                                },
                                {
                                    "_key": "placeholder",
                                    "_value": "Input",
                                    "_type": "kv",
                                    "_attrDef": "p",
                                    "_useAsLabel": true
                                },
                                {
                                    "_key": "value",
                                    "_value": "",
                                    "_type": "kv",
                                    "_attrDef": "p"
                                },
                                {
                                    "_key": "required",
                                    "_value": "required",
                                    "_type": "a",
                                    "_attrDef": "p"
                                },
                                {
                                    "_key": "[(ngModel)]",
                                    "_value": "dm.risk_general_coll.risk_title",
                                    "_type": "kv",
                                    "_attrDef": "p"
                                },
                                {
                                    "_key": "color",
                                    "_value": "",
                                    "_type": "kv",
                                    "_attrDef": "p"
                                },
                                {
                                    "_key": "name",
                                    "_value": "",
                                    "_type": "kv",
                                    "_attrDef": "p"
                                },
                                {
                                    "_key": "type",
                                    "_value": "",
                                    "_type": "kv",
                                    "_attrDef": "p"
                                },
                                {
                                    "_key": "[formControl]",
                                    "_value": "",
                                    "_type": "kv",
                                    "_attrDef": "p"
                                },
                                {
                                    "_key": "readonly",
                                    "_value": "",
                                    "_type": "kv",
                                    "_attrDef": "p"
                                },
                                {
                                    "_key": "[disabled]",
                                    "_value": "",
                                    "_type": "kv",
                                    "_attrDef": "p"
                                },
                                {
                                    "_key": "id",
                                    "_value": "",
                                    "_type": "kv",
                                    "_attrDef": "p"
                                },
                                {
                                    "_key": "matError",
                                    "_value": [],
                                    "_type": "a",
                                    "_attrDef": "p",
                                    "_visibility": true
                                },
                                {
                                    "_key": "inputHint",
                                    "_value": [],
                                    "_type": "a",
                                    "_attrDef": "p",
                                    "_visibility": true
                                },
                                {
                                    "_key": "(prefixIconClick)",
                                    "_value": "",
                                    "_type": "a",
                                    "_attrDef": "p",
                                    "_visibility": true
                                },
                                {
                                    "_key": "(suffixIconClick)",
                                    "_value": "",
                                    "_type": "a",
                                    "_attrDef": "p",
                                    "_visibility": true
                                },
                                {
                                    "_key": "Label",
                                    "_value": "",
                                    "_type": "a",
                                    "_attrDef": "p",
                                    "_visibility": true
                                },
                                {
                                    "_key": "Suffix Icon",
                                    "_value": "",
                                    "_type": "a",
                                    "_attrDef": "p",
                                    "_visibility": true
                                },
                                {
                                    "_key": "Prefix Icon",
                                    "_value": "",
                                    "_type": "a",
                                    "_attrDef": "p",
                                    "_visibility": true
                                },
                                {
                                    "_key": "Prefix",
                                    "_value": "",
                                    "_type": "a",
                                    "_attrDef": "p",
                                    "_visibility": true
                                },
                                {
                                    "_key": "Suffix",
                                    "_value": "",
                                    "_type": "a",
                                    "_attrDef": "p",
                                    "_visibility": true
                                },
                                {
                                    "_key": "[appearance]",
                                    "_value": "'legacy'",
                                    "_type": "a",
                                    "_attrDef": "p"
                                },
                                {
                                    "_key": "[floatLabel]",
                                    "_value": "'auto'",
                                    "_type": "kv",
                                    "_attrDef": "p"
                                }
                            ]
                        }
                    },
                    "d4b1fe54-dec6-05ba-c0a2-5635df2bd516": {
                        "paletteKey": "FlexLayoutRow",
                        "parentEditorKey": "9e5b7e36-58d7-a2bf-d79d-2ea2096fd400",
                        "designerReference": [
                            {
                                "_key": "componentLabel",
                                "_value": "Row",
                                "_type": "kv",
                                "_attrDef": "p",
                                "_useAsLabel": true
                            },
                            {
                                "_key": "style",
                                "_value": "",
                                "_type": "kv",
                                "_attrDef": "p"
                            },
                            {
                                "_key": "class",
                                "_value": "",
                                "_type": "kv",
                                "_attrDef": "p"
                            },
                            {
                                "_key": "fxFlex",
                                "_value": "",
                                "_type": "kv",
                                "_attrDef": "p"
                            },
                            {
                                "_key": "fxLayoutGap",
                                "_value": "10px",
                                "_type": "kv",
                                "_attrDef": "p"
                            },
                            {
                                "_key": "wrap",
                                "_value": "wrap",
                                "_type": "a",
                                "_attrDef": "p"
                            },
                            {
                                "_key": "layoutAlign",
                                "_value": "center",
                                "_type": "a",
                                "_attrDef": "p"
                            },
                            {
                                "_key": "pLayoutAlign",
                                "_value": "center",
                                "_type": "a",
                                "_attrDef": "p"
                            },
                            {
                                "_key": "fxShow",
                                "_value": "true",
                                "_type": "kv",
                                "_attrDef": "p"
                            },
                            {
                                "_key": "fxHide",
                                "_value": "false",
                                "_type": "kv",
                                "_attrDef": "p"
                            }
                        ],
                        "acf015f9-3ec0-fb09-f8c0-c5aa03437886": {
                            "paletteKey": "NG-Paragraph",
                            "parentEditorKey": "d4b1fe54-dec6-05ba-c0a2-5635df2bd516",
                            "designerReference": [
                                {
                                    "_key": "style",
                                    "_value": "",
                                    "_type": "kv",
                                    "_attrDef": "p"
                                },
                                {
                                    "_key": "class",
                                    "_value": "",
                                    "_type": "kv",
                                    "_attrDef": "p"
                                },
                                {
                                    "_key": "text",
                                    "_value": "Valid From",
                                    "_type": "a",
                                    "_attrDef": "p",
                                    "_useAsLabel": true
                                },
                                {
                                    "_key": "align",
                                    "_value": "",
                                    "_type": "kv",
                                    "_attrDef": "p"
                                }
                            ]
                        },
                        "f53ef6d6-6347-b954-38cc-54865e8820af": {
                            "paletteKey": "NG-DatePicker",
                            "parentEditorKey": "d4b1fe54-dec6-05ba-c0a2-5635df2bd516",
                            "isAdvancedComponent": true,
                            "designerReference": [
                                {
                                    "_key": "style",
                                    "_value": "",
                                    "_type": "kv",
                                    "_attrDef": "p"
                                },
                                {
                                    "_key": "class",
                                    "_value": "",
                                    "_type": "kv",
                                    "_attrDef": "p"
                                },
                                {
                                    "_key": "placeholder",
                                    "_value": "Date Picker",
                                    "_type": "kv",
                                    "_attrDef": "p",
                                    "_useAsLabel": true
                                },
                                {
                                    "_key": "value",
                                    "_value": "",
                                    "_type": "kv",
                                    "_attrDef": "p"
                                },
                                {
                                    "_key": "[min]",
                                    "_value": "",
                                    "_type": "kv",
                                    "_attrDef": "p"
                                },
                                {
                                    "_key": "[max]",
                                    "_value": "",
                                    "_type": "kv",
                                    "_attrDef": "p"
                                },
                                {
                                    "_key": "[startAt]",
                                    "_value": "",
                                    "_type": "kv",
                                    "_attrDef": "p"
                                },
                                {
                                    "_key": "startView",
                                    "_value": "",
                                    "_type": "kv",
                                    "_attrDef": "p"
                                },
                                {
                                    "_key": "touchUi",
                                    "_value": "",
                                    "_type": "kv",
                                    "_attrDef": "p"
                                },
                                {
                                    "_key": "id",
                                    "_value": "",
                                    "_type": "kv",
                                    "_attrDef": "p"
                                },
                                {
                                    "_key": "(dateChange)",
                                    "_value": "",
                                    "_type": "kv",
                                    "_attrDef": "p"
                                },
                                {
                                    "_key": "(dateInput)",
                                    "_value": "",
                                    "_type": "kv",
                                    "_attrDef": "p"
                                },
                                {
                                    "_key": "[opened]",
                                    "_value": "",
                                    "_type": "kv",
                                    "_attrDef": "p"
                                },
                                {
                                    "_key": "[disabled]",
                                    "_value": "",
                                    "_type": "kv",
                                    "_attrDef": "p"
                                },
                                {
                                    "_key": "(open)",
                                    "_value": "",
                                    "_type": "kv",
                                    "_attrDef": "p"
                                },
                                {
                                    "_key": "(close)",
                                    "_value": "",
                                    "_type": "kv",
                                    "_attrDef": "p"
                                },
                                {
                                    "_key": "[matDatepickerFilter]",
                                    "_value": "",
                                    "_type": "kv",
                                    "_attrDef": "p"
                                },
                                {
                                    "_key": "[(ngModel)]",
                                    "_value": "dm.risk_general_coll.valid_from",
                                    "_type": "kv",
                                    "_attrDef": "p"
                                },
                                {
                                    "_key": "name",
                                    "_value": "",
                                    "_type": "kv",
                                    "_attrDef": "p"
                                },
                                {
                                    "_key": "picker",
                                    "_value": "picker1",
                                    "_type": "ma",
                                    "_attrDef": "p"
                                },
                                {
                                    "_key": "ngModel",
                                    "_value": "",
                                    "_type": "vk",
                                    "_attrDef": "p"
                                },
                                {
                                    "_key": "matError",
                                    "_value": [],
                                    "_type": "a",
                                    "_attrDef": "p",
                                    "_visibility": true
                                },
                                {
                                    "_key": "required",
                                    "_value": "required",
                                    "_type": "a",
                                    "_attrDef": "p"
                                }
                            ]
                        }
                    },
                    "64ef8460-903f-9392-f800-e7b890ca2c42": {
                        "paletteKey": "FlexLayoutRow",
                        "parentEditorKey": "9e5b7e36-58d7-a2bf-d79d-2ea2096fd400",
                        "designerReference": [
                            {
                                "_key": "componentLabel",
                                "_value": "Row",
                                "_type": "kv",
                                "_attrDef": "p",
                                "_useAsLabel": true
                            },
                            {
                                "_key": "style",
                                "_value": "",
                                "_type": "kv",
                                "_attrDef": "p"
                            },
                            {
                                "_key": "class",
                                "_value": "",
                                "_type": "kv",
                                "_attrDef": "p"
                            },
                            {
                                "_key": "fxFlex",
                                "_value": "",
                                "_type": "kv",
                                "_attrDef": "p"
                            },
                            {
                                "_key": "fxLayoutGap",
                                "_value": "10px",
                                "_type": "kv",
                                "_attrDef": "p"
                            },
                            {
                                "_key": "wrap",
                                "_value": "wrap",
                                "_type": "a",
                                "_attrDef": "p"
                            },
                            {
                                "_key": "layoutAlign",
                                "_value": "center",
                                "_type": "a",
                                "_attrDef": "p"
                            },
                            {
                                "_key": "pLayoutAlign",
                                "_value": "center",
                                "_type": "a",
                                "_attrDef": "p"
                            },
                            {
                                "_key": "fxShow",
                                "_value": "true",
                                "_type": "kv",
                                "_attrDef": "p"
                            },
                            {
                                "_key": "fxHide",
                                "_value": "false",
                                "_type": "kv",
                                "_attrDef": "p"
                            }
                        ],
                        "366b737a-f8d2-3d1a-fc8f-abf499548021": {
                            "paletteKey": "NG-Paragraph",
                            "parentEditorKey": "64ef8460-903f-9392-f800-e7b890ca2c42",
                            "designerReference": [
                                {
                                    "_key": "style",
                                    "_value": "",
                                    "_type": "kv",
                                    "_attrDef": "p"
                                },
                                {
                                    "_key": "class",
                                    "_value": "",
                                    "_type": "kv",
                                    "_attrDef": "p"
                                },
                                {
                                    "_key": "text",
                                    "_value": "Created By",
                                    "_type": "a",
                                    "_attrDef": "p",
                                    "_useAsLabel": true
                                },
                                {
                                    "_key": "align",
                                    "_value": "",
                                    "_type": "kv",
                                    "_attrDef": "p"
                                }
                            ]
                        },
                        "e14c80d6-11e8-23ef-c165-3a05d0df43b8": {
                            "paletteKey": "NG-Input",
                            "parentEditorKey": "64ef8460-903f-9392-f800-e7b890ca2c42",
                            "isAdvancedComponent": true,
                            "designerReference": [
                                {
                                    "_key": "style",
                                    "_value": "",
                                    "_type": "kv",
                                    "_attrDef": "p"
                                },
                                {
                                    "_key": "class",
                                    "_value": "",
                                    "_type": "kv",
                                    "_attrDef": "p"
                                },
                                {
                                    "_key": "placeholder",
                                    "_value": "Input",
                                    "_type": "kv",
                                    "_attrDef": "p",
                                    "_useAsLabel": true
                                },
                                {
                                    "_key": "value",
                                    "_value": "",
                                    "_type": "kv",
                                    "_attrDef": "p"
                                },
                                {
                                    "_key": "required",
                                    "_value": "required",
                                    "_type": "a",
                                    "_attrDef": "p"
                                },
                                {
                                    "_key": "[(ngModel)]",
                                    "_value": "dm.risk_general_coll.created_by",
                                    "_type": "kv",
                                    "_attrDef": "p"
                                },
                                {
                                    "_key": "color",
                                    "_value": "",
                                    "_type": "kv",
                                    "_attrDef": "p"
                                },
                                {
                                    "_key": "name",
                                    "_value": "",
                                    "_type": "kv",
                                    "_attrDef": "p"
                                },
                                {
                                    "_key": "type",
                                    "_value": "",
                                    "_type": "kv",
                                    "_attrDef": "p"
                                },
                                {
                                    "_key": "[formControl]",
                                    "_value": "",
                                    "_type": "kv",
                                    "_attrDef": "p"
                                },
                                {
                                    "_key": "readonly",
                                    "_value": "",
                                    "_type": "kv",
                                    "_attrDef": "p"
                                },
                                {
                                    "_key": "[disabled]",
                                    "_value": "",
                                    "_type": "kv",
                                    "_attrDef": "p"
                                },
                                {
                                    "_key": "id",
                                    "_value": "",
                                    "_type": "kv",
                                    "_attrDef": "p"
                                },
                                {
                                    "_key": "matError",
                                    "_value": [],
                                    "_type": "a",
                                    "_attrDef": "p",
                                    "_visibility": true
                                },
                                {
                                    "_key": "inputHint",
                                    "_value": [],
                                    "_type": "a",
                                    "_attrDef": "p",
                                    "_visibility": true
                                },
                                {
                                    "_key": "(prefixIconClick)",
                                    "_value": "",
                                    "_type": "a",
                                    "_attrDef": "p",
                                    "_visibility": true
                                },
                                {
                                    "_key": "(suffixIconClick)",
                                    "_value": "",
                                    "_type": "a",
                                    "_attrDef": "p",
                                    "_visibility": true
                                },
                                {
                                    "_key": "Label",
                                    "_value": "",
                                    "_type": "a",
                                    "_attrDef": "p",
                                    "_visibility": true
                                },
                                {
                                    "_key": "Suffix Icon",
                                    "_value": "",
                                    "_type": "a",
                                    "_attrDef": "p",
                                    "_visibility": true
                                },
                                {
                                    "_key": "Prefix Icon",
                                    "_value": "",
                                    "_type": "a",
                                    "_attrDef": "p",
                                    "_visibility": true
                                },
                                {
                                    "_key": "Prefix",
                                    "_value": "",
                                    "_type": "a",
                                    "_attrDef": "p",
                                    "_visibility": true
                                },
                                {
                                    "_key": "Suffix",
                                    "_value": "",
                                    "_type": "a",
                                    "_attrDef": "p",
                                    "_visibility": true
                                },
                                {
                                    "_key": "[appearance]",
                                    "_value": "'legacy'",
                                    "_type": "a",
                                    "_attrDef": "p"
                                },
                                {
                                    "_key": "[floatLabel]",
                                    "_value": "'auto'",
                                    "_type": "kv",
                                    "_attrDef": "p"
                                }
                            ]
                        }
                    }
                },
                "c4175532-8e78-09ca-037e-c2296df9eabf": {
                    "paletteKey": "FlexLayoutCol",
                    "parentEditorKey": "4c8b1310-d056-9ce1-10ff-e25d636ddd01",
                    "designerReference": [
                        {
                            "_key": "componentLabel",
                            "_value": "Column",
                            "_type": "kv",
                            "_attrDef": "p",
                            "_useAsLabel": true
                        },
                        {
                            "_key": "style",
                            "_value": "",
                            "_type": "kv",
                            "_attrDef": "p"
                        },
                        {
                            "_key": "class",
                            "_value": "",
                            "_type": "kv",
                            "_attrDef": "p"
                        },
                        {
                            "_key": "fxFlex",
                            "_value": "",
                            "_type": "kv",
                            "_attrDef": "p"
                        },
                        {
                            "_key": "fxLayoutGap",
                            "_value": "",
                            "_type": "kv",
                            "_attrDef": "p"
                        },
                        {
                            "_key": "wrap",
                            "_value": "wrap",
                            "_type": "a",
                            "_attrDef": "p"
                        },
                        {
                            "_key": "layoutAlign",
                            "_value": "center",
                            "_type": "a",
                            "_attrDef": "p"
                        },
                        {
                            "_key": "pLayoutAlign",
                            "_value": "center",
                            "_type": "a",
                            "_attrDef": "p"
                        },
                        {
                            "_key": "fxShow",
                            "_value": "true",
                            "_type": "kv",
                            "_attrDef": "p"
                        },
                        {
                            "_key": "fxHide",
                            "_value": "false",
                            "_type": "kv",
                            "_attrDef": "p"
                        }
                    ],
                    "97f4dd66-93d1-18c2-f5d1-eddaca60ad2f": {
                        "paletteKey": "FlexLayoutRow",
                        "parentEditorKey": "c4175532-8e78-09ca-037e-c2296df9eabf",
                        "designerReference": [
                            {
                                "_key": "componentLabel",
                                "_value": "Row",
                                "_type": "kv",
                                "_attrDef": "p",
                                "_useAsLabel": true
                            },
                            {
                                "_key": "style",
                                "_value": "",
                                "_type": "kv",
                                "_attrDef": "p"
                            },
                            {
                                "_key": "class",
                                "_value": "",
                                "_type": "kv",
                                "_attrDef": "p"
                            },
                            {
                                "_key": "fxFlex",
                                "_value": "",
                                "_type": "kv",
                                "_attrDef": "p"
                            },
                            {
                                "_key": "fxLayoutGap",
                                "_value": "10px",
                                "_type": "kv",
                                "_attrDef": "p"
                            },
                            {
                                "_key": "wrap",
                                "_value": "wrap",
                                "_type": "a",
                                "_attrDef": "p"
                            },
                            {
                                "_key": "layoutAlign",
                                "_value": "center",
                                "_type": "a",
                                "_attrDef": "p"
                            },
                            {
                                "_key": "pLayoutAlign",
                                "_value": "center",
                                "_type": "a",
                                "_attrDef": "p"
                            },
                            {
                                "_key": "fxShow",
                                "_value": "true",
                                "_type": "kv",
                                "_attrDef": "p"
                            },
                            {
                                "_key": "fxHide",
                                "_value": "false",
                                "_type": "kv",
                                "_attrDef": "p"
                            }
                        ],
                        "bc7c2049-1b0b-c97d-3e59-ee937133d200": {
                            "paletteKey": "NG-Paragraph",
                            "parentEditorKey": "97f4dd66-93d1-18c2-f5d1-eddaca60ad2f",
                            "designerReference": [
                                {
                                    "_key": "style",
                                    "_value": "",
                                    "_type": "kv",
                                    "_attrDef": "p"
                                },
                                {
                                    "_key": "class",
                                    "_value": "",
                                    "_type": "kv",
                                    "_attrDef": "p"
                                },
                                {
                                    "_key": "text",
                                    "_value": "Risk Description",
                                    "_type": "a",
                                    "_attrDef": "p",
                                    "_useAsLabel": true
                                },
                                {
                                    "_key": "align",
                                    "_value": "",
                                    "_type": "kv",
                                    "_attrDef": "p"
                                }
                            ]
                        },
                        "2e17eef3-9dbc-8152-27df-0497bd04f6d7": {
                            "paletteKey": "NG-Input",
                            "parentEditorKey": "97f4dd66-93d1-18c2-f5d1-eddaca60ad2f",
                            "isAdvancedComponent": true,
                            "designerReference": [
                                {
                                    "_key": "style",
                                    "_value": "",
                                    "_type": "kv",
                                    "_attrDef": "p"
                                },
                                {
                                    "_key": "class",
                                    "_value": "",
                                    "_type": "kv",
                                    "_attrDef": "p"
                                },
                                {
                                    "_key": "placeholder",
                                    "_value": "Input",
                                    "_type": "kv",
                                    "_attrDef": "p",
                                    "_useAsLabel": true
                                },
                                {
                                    "_key": "value",
                                    "_value": "",
                                    "_type": "kv",
                                    "_attrDef": "p"
                                },
                                {
                                    "_key": "required",
                                    "_value": "required",
                                    "_type": "a",
                                    "_attrDef": "p"
                                },
                                {
                                    "_key": "[(ngModel)]",
                                    "_value": "dm.risk_general_coll.risk_desc",
                                    "_type": "kv",
                                    "_attrDef": "p"
                                },
                                {
                                    "_key": "color",
                                    "_value": "",
                                    "_type": "kv",
                                    "_attrDef": "p"
                                },
                                {
                                    "_key": "name",
                                    "_value": "",
                                    "_type": "kv",
                                    "_attrDef": "p"
                                },
                                {
                                    "_key": "type",
                                    "_value": "",
                                    "_type": "kv",
                                    "_attrDef": "p"
                                },
                                {
                                    "_key": "[formControl]",
                                    "_value": "",
                                    "_type": "kv",
                                    "_attrDef": "p"
                                },
                                {
                                    "_key": "readonly",
                                    "_value": "",
                                    "_type": "kv",
                                    "_attrDef": "p"
                                },
                                {
                                    "_key": "[disabled]",
                                    "_value": "",
                                    "_type": "kv",
                                    "_attrDef": "p"
                                },
                                {
                                    "_key": "id",
                                    "_value": "",
                                    "_type": "kv",
                                    "_attrDef": "p"
                                },
                                {
                                    "_key": "matError",
                                    "_value": [],
                                    "_type": "a",
                                    "_attrDef": "p",
                                    "_visibility": true
                                },
                                {
                                    "_key": "inputHint",
                                    "_value": [],
                                    "_type": "a",
                                    "_attrDef": "p",
                                    "_visibility": true
                                },
                                {
                                    "_key": "(prefixIconClick)",
                                    "_value": "",
                                    "_type": "a",
                                    "_attrDef": "p",
                                    "_visibility": true
                                },
                                {
                                    "_key": "(suffixIconClick)",
                                    "_value": "",
                                    "_type": "a",
                                    "_attrDef": "p",
                                    "_visibility": true
                                },
                                {
                                    "_key": "Label",
                                    "_value": "",
                                    "_type": "a",
                                    "_attrDef": "p",
                                    "_visibility": true
                                },
                                {
                                    "_key": "Suffix Icon",
                                    "_value": "",
                                    "_type": "a",
                                    "_attrDef": "p",
                                    "_visibility": true
                                },
                                {
                                    "_key": "Prefix Icon",
                                    "_value": "",
                                    "_type": "a",
                                    "_attrDef": "p",
                                    "_visibility": true
                                },
                                {
                                    "_key": "Prefix",
                                    "_value": "",
                                    "_type": "a",
                                    "_attrDef": "p",
                                    "_visibility": true
                                },
                                {
                                    "_key": "Suffix",
                                    "_value": "",
                                    "_type": "a",
                                    "_attrDef": "p",
                                    "_visibility": true
                                },
                                {
                                    "_key": "[appearance]",
                                    "_value": "'legacy'",
                                    "_type": "a",
                                    "_attrDef": "p"
                                },
                                {
                                    "_key": "[floatLabel]",
                                    "_value": "'auto'",
                                    "_type": "kv",
                                    "_attrDef": "p"
                                }
                            ]
                        }
                    },
                    "24e2dc4e-22e2-44d7-c4ee-938b9842412b": {
                        "paletteKey": "FlexLayoutRow",
                        "parentEditorKey": "c4175532-8e78-09ca-037e-c2296df9eabf",
                        "designerReference": [
                            {
                                "_key": "componentLabel",
                                "_value": "Row",
                                "_type": "kv",
                                "_attrDef": "p",
                                "_useAsLabel": true
                            },
                            {
                                "_key": "style",
                                "_value": "",
                                "_type": "kv",
                                "_attrDef": "p"
                            },
                            {
                                "_key": "class",
                                "_value": "",
                                "_type": "kv",
                                "_attrDef": "p"
                            },
                            {
                                "_key": "fxFlex",
                                "_value": "",
                                "_type": "kv",
                                "_attrDef": "p"
                            },
                            {
                                "_key": "fxLayoutGap",
                                "_value": "10px",
                                "_type": "kv",
                                "_attrDef": "p"
                            },
                            {
                                "_key": "wrap",
                                "_value": "wrap",
                                "_type": "a",
                                "_attrDef": "p"
                            },
                            {
                                "_key": "layoutAlign",
                                "_value": "center",
                                "_type": "a",
                                "_attrDef": "p"
                            },
                            {
                                "_key": "pLayoutAlign",
                                "_value": "center",
                                "_type": "a",
                                "_attrDef": "p"
                            },
                            {
                                "_key": "fxShow",
                                "_value": "true",
                                "_type": "kv",
                                "_attrDef": "p"
                            },
                            {
                                "_key": "fxHide",
                                "_value": "false",
                                "_type": "kv",
                                "_attrDef": "p"
                            }
                        ],
                        "30b674fb-f48f-208c-bfe1-37b31628eff6": {
                            "paletteKey": "NG-Paragraph",
                            "parentEditorKey": "24e2dc4e-22e2-44d7-c4ee-938b9842412b",
                            "designerReference": [
                                {
                                    "_key": "style",
                                    "_value": "",
                                    "_type": "kv",
                                    "_attrDef": "p"
                                },
                                {
                                    "_key": "class",
                                    "_value": "",
                                    "_type": "kv",
                                    "_attrDef": "p"
                                },
                                {
                                    "_key": "text",
                                    "_value": "Valid To",
                                    "_type": "a",
                                    "_attrDef": "p",
                                    "_useAsLabel": true
                                },
                                {
                                    "_key": "align",
                                    "_value": "",
                                    "_type": "kv",
                                    "_attrDef": "p"
                                }
                            ]
                        },
                        "1487672b-83cd-1c47-7513-5a6335e48461": {
                            "paletteKey": "NG-DatePicker",
                            "parentEditorKey": "24e2dc4e-22e2-44d7-c4ee-938b9842412b",
                            "isAdvancedComponent": true,
                            "designerReference": [
                                {
                                    "_key": "style",
                                    "_value": "",
                                    "_type": "kv",
                                    "_attrDef": "p"
                                },
                                {
                                    "_key": "class",
                                    "_value": "",
                                    "_type": "kv",
                                    "_attrDef": "p"
                                },
                                {
                                    "_key": "placeholder",
                                    "_value": "Date Picker",
                                    "_type": "kv",
                                    "_attrDef": "p",
                                    "_useAsLabel": true
                                },
                                {
                                    "_key": "value",
                                    "_value": "",
                                    "_type": "kv",
                                    "_attrDef": "p"
                                },
                                {
                                    "_key": "[min]",
                                    "_value": "",
                                    "_type": "kv",
                                    "_attrDef": "p"
                                },
                                {
                                    "_key": "[max]",
                                    "_value": "",
                                    "_type": "kv",
                                    "_attrDef": "p"
                                },
                                {
                                    "_key": "[startAt]",
                                    "_value": "",
                                    "_type": "kv",
                                    "_attrDef": "p"
                                },
                                {
                                    "_key": "startView",
                                    "_value": "",
                                    "_type": "kv",
                                    "_attrDef": "p"
                                },
                                {
                                    "_key": "touchUi",
                                    "_value": "",
                                    "_type": "kv",
                                    "_attrDef": "p"
                                },
                                {
                                    "_key": "id",
                                    "_value": "",
                                    "_type": "kv",
                                    "_attrDef": "p"
                                },
                                {
                                    "_key": "(dateChange)",
                                    "_value": "",
                                    "_type": "kv",
                                    "_attrDef": "p"
                                },
                                {
                                    "_key": "(dateInput)",
                                    "_value": "",
                                    "_type": "kv",
                                    "_attrDef": "p"
                                },
                                {
                                    "_key": "[opened]",
                                    "_value": "",
                                    "_type": "kv",
                                    "_attrDef": "p"
                                },
                                {
                                    "_key": "[disabled]",
                                    "_value": "",
                                    "_type": "kv",
                                    "_attrDef": "p"
                                },
                                {
                                    "_key": "(open)",
                                    "_value": "",
                                    "_type": "kv",
                                    "_attrDef": "p"
                                },
                                {
                                    "_key": "(close)",
                                    "_value": "",
                                    "_type": "kv",
                                    "_attrDef": "p"
                                },
                                {
                                    "_key": "[matDatepickerFilter]",
                                    "_value": "",
                                    "_type": "kv",
                                    "_attrDef": "p"
                                },
                                {
                                    "_key": "[(ngModel)]",
                                    "_value": "dm.risk_general_coll.valid_to",
                                    "_type": "kv",
                                    "_attrDef": "p"
                                },
                                {
                                    "_key": "name",
                                    "_value": "",
                                    "_type": "kv",
                                    "_attrDef": "p"
                                },
                                {
                                    "_key": "picker",
                                    "_value": "picker2",
                                    "_type": "ma",
                                    "_attrDef": "p"
                                },
                                {
                                    "_key": "ngModel",
                                    "_value": "",
                                    "_type": "vk",
                                    "_attrDef": "p"
                                },
                                {
                                    "_key": "matError",
                                    "_value": [],
                                    "_type": "a",
                                    "_attrDef": "p",
                                    "_visibility": true
                                },
                                {
                                    "_key": "required",
                                    "_value": "required",
                                    "_type": "a",
                                    "_attrDef": "p"
                                }
                            ]
                        }
                    },
                    "fad28a54-67f1-2253-5869-fd58a3d8078a": {
                        "paletteKey": "FlexLayoutRow",
                        "parentEditorKey": "c4175532-8e78-09ca-037e-c2296df9eabf",
                        "designerReference": [
                            {
                                "_key": "componentLabel",
                                "_value": "Row",
                                "_type": "kv",
                                "_attrDef": "p",
                                "_useAsLabel": true
                            },
                            {
                                "_key": "style",
                                "_value": "",
                                "_type": "kv",
                                "_attrDef": "p"
                            },
                            {
                                "_key": "class",
                                "_value": "",
                                "_type": "kv",
                                "_attrDef": "p"
                            },
                            {
                                "_key": "fxFlex",
                                "_value": "",
                                "_type": "kv",
                                "_attrDef": "p"
                            },
                            {
                                "_key": "fxLayoutGap",
                                "_value": "10px",
                                "_type": "kv",
                                "_attrDef": "p"
                            },
                            {
                                "_key": "wrap",
                                "_value": "wrap",
                                "_type": "a",
                                "_attrDef": "p"
                            },
                            {
                                "_key": "layoutAlign",
                                "_value": "center",
                                "_type": "a",
                                "_attrDef": "p"
                            },
                            {
                                "_key": "pLayoutAlign",
                                "_value": "center",
                                "_type": "a",
                                "_attrDef": "p"
                            },
                            {
                                "_key": "fxShow",
                                "_value": "true",
                                "_type": "kv",
                                "_attrDef": "p"
                            },
                            {
                                "_key": "fxHide",
                                "_value": "false",
                                "_type": "kv",
                                "_attrDef": "p"
                            }
                        ],
                        "f424b221-9612-181c-ddf7-99c69a0edc4c": {
                            "paletteKey": "NG-Paragraph",
                            "parentEditorKey": "fad28a54-67f1-2253-5869-fd58a3d8078a",
                            "designerReference": [
                                {
                                    "_key": "style",
                                    "_value": "",
                                    "_type": "kv",
                                    "_attrDef": "p"
                                },
                                {
                                    "_key": "class",
                                    "_value": "",
                                    "_type": "kv",
                                    "_attrDef": "p"
                                },
                                {
                                    "_key": "text",
                                    "_value": "Created Date",
                                    "_type": "a",
                                    "_attrDef": "p",
                                    "_useAsLabel": true
                                },
                                {
                                    "_key": "align",
                                    "_value": "",
                                    "_type": "kv",
                                    "_attrDef": "p"
                                }
                            ]
                        },
                        "6ababe3d-4fc7-ce08-8994-fe999705e09b": {
                            "paletteKey": "NG-DatePicker",
                            "parentEditorKey": "fad28a54-67f1-2253-5869-fd58a3d8078a",
                            "isAdvancedComponent": true,
                            "designerReference": [
                                {
                                    "_key": "style",
                                    "_value": "",
                                    "_type": "kv",
                                    "_attrDef": "p"
                                },
                                {
                                    "_key": "class",
                                    "_value": "",
                                    "_type": "kv",
                                    "_attrDef": "p"
                                },
                                {
                                    "_key": "placeholder",
                                    "_value": "Date Picker",
                                    "_type": "kv",
                                    "_attrDef": "p",
                                    "_useAsLabel": true
                                },
                                {
                                    "_key": "value",
                                    "_value": "",
                                    "_type": "kv",
                                    "_attrDef": "p"
                                },
                                {
                                    "_key": "[min]",
                                    "_value": "",
                                    "_type": "kv",
                                    "_attrDef": "p"
                                },
                                {
                                    "_key": "[max]",
                                    "_value": "",
                                    "_type": "kv",
                                    "_attrDef": "p"
                                },
                                {
                                    "_key": "[startAt]",
                                    "_value": "",
                                    "_type": "kv",
                                    "_attrDef": "p"
                                },
                                {
                                    "_key": "startView",
                                    "_value": "",
                                    "_type": "kv",
                                    "_attrDef": "p"
                                },
                                {
                                    "_key": "touchUi",
                                    "_value": "",
                                    "_type": "kv",
                                    "_attrDef": "p"
                                },
                                {
                                    "_key": "id",
                                    "_value": "",
                                    "_type": "kv",
                                    "_attrDef": "p"
                                },
                                {
                                    "_key": "(dateChange)",
                                    "_value": "",
                                    "_type": "kv",
                                    "_attrDef": "p"
                                },
                                {
                                    "_key": "(dateInput)",
                                    "_value": "",
                                    "_type": "kv",
                                    "_attrDef": "p"
                                },
                                {
                                    "_key": "[opened]",
                                    "_value": "",
                                    "_type": "kv",
                                    "_attrDef": "p"
                                },
                                {
                                    "_key": "[disabled]",
                                    "_value": "",
                                    "_type": "kv",
                                    "_attrDef": "p"
                                },
                                {
                                    "_key": "(open)",
                                    "_value": "",
                                    "_type": "kv",
                                    "_attrDef": "p"
                                },
                                {
                                    "_key": "(close)",
                                    "_value": "",
                                    "_type": "kv",
                                    "_attrDef": "p"
                                },
                                {
                                    "_key": "[matDatepickerFilter]",
                                    "_value": "",
                                    "_type": "kv",
                                    "_attrDef": "p"
                                },
                                {
                                    "_key": "[(ngModel)]",
                                    "_value": "dm.risk_general_coll.created_date",
                                    "_type": "kv",
                                    "_attrDef": "p"
                                },
                                {
                                    "_key": "name",
                                    "_value": "",
                                    "_type": "kv",
                                    "_attrDef": "p"
                                },
                                {
                                    "_key": "picker",
                                    "_value": "picker3",
                                    "_type": "ma",
                                    "_attrDef": "p"
                                },
                                {
                                    "_key": "ngModel",
                                    "_value": "",
                                    "_type": "vk",
                                    "_attrDef": "p"
                                },
                                {
                                    "_key": "matError",
                                    "_value": [],
                                    "_type": "a",
                                    "_attrDef": "p",
                                    "_visibility": true
                                },
                                {
                                    "_key": "required",
                                    "_value": "required",
                                    "_type": "a",
                                    "_attrDef": "p"
                                }
                            ]
                        }
                    }
                }
            },
            "642d9e7a-c48b-0e8c-b521-8571cd73f368": {
                "paletteKey": "FlexLayoutRow",
                "parentEditorKey": "604acac2-8471-0964-66df-242746fb0ed5",
                "designerReference": [
                    {
                        "_key": "componentLabel",
                        "_value": "Row",
                        "_type": "kv",
                        "_attrDef": "p",
                        "_useAsLabel": true
                    },
                    {
                        "_key": "style",
                        "_value": "",
                        "_type": "kv",
                        "_attrDef": "p"
                    },
                    {
                        "_key": "class",
                        "_value": "",
                        "_type": "kv",
                        "_attrDef": "p"
                    },
                    {
                        "_key": "fxFlex",
                        "_value": "",
                        "_type": "kv",
                        "_attrDef": "p"
                    },
                    {
                        "_key": "fxLayoutGap",
                        "_value": "20px",
                        "_type": "kv",
                        "_attrDef": "p"
                    },
                    {
                        "_key": "wrap",
                        "_value": "wrap",
                        "_type": "a",
                        "_attrDef": "p"
                    },
                    {
                        "_key": "layoutAlign",
                        "_value": "start",
                        "_type": "a",
                        "_attrDef": "p"
                    },
                    {
                        "_key": "pLayoutAlign",
                        "_value": "stretch",
                        "_type": "a",
                        "_attrDef": "p"
                    },
                    {
                        "_key": "fxShow",
                        "_value": "true",
                        "_type": "kv",
                        "_attrDef": "p"
                    },
                    {
                        "_key": "fxHide",
                        "_value": "false",
                        "_type": "kv",
                        "_attrDef": "p"
                    }
                ],
                "82dc34a9-8fd7-ef96-3c7e-4e1c9ed3c434": {
                    "paletteKey": "NG-RaisedButton",
                    "parentEditorKey": "642d9e7a-c48b-0e8c-b521-8571cd73f368",
                    "designerReference": [
                        {
                            "_key": "style",
                            "_value": "",
                            "_type": "kv",
                            "_attrDef": "p"
                        },
                        {
                            "_key": "class",
                            "_value": "",
                            "_type": "kv",
                            "_attrDef": "p"
                        },
                        {
                            "_key": "buttonname",
                            "_value": "Save",
                            "_type": "a",
                            "_attrDef": "p",
                            "_useAsLabel": true
                        },
                        {
                            "_key": "color",
                            "_value": "",
                            "_type": "kv",
                            "_attrDef": "p"
                        },
                        {
                            "_key": "(click)",
                            "_value": "put('risk_general_coll', dm.risk_general_coll)",
                            "_type": "kv",
                            "_attrDef": "p"
                        },
                        {
                            "_key": "[disabled]",
                            "_value": "",
                            "_type": "kv",
                            "_attrDef": "p"
                        },
                        {
                            "_key": "[disableRipple]",
                            "_value": "",
                            "_type": "kv",
                            "_attrDef": "p"
                        },
                        {
                            "_key": "type",
                            "_value": "",
                            "_type": "kv",
                            "_attrDef": "p"
                        },
                        {
                            "_key": "routerLink",
                            "_value": "",
                            "_type": "kv",
                            "_attrDef": "p"
                        }
                    ]
                },
                "04fc71ea-c4dd-d5b7-afe9-1af679c788a5": {
                    "paletteKey": "NG-RaisedButton",
                    "parentEditorKey": "642d9e7a-c48b-0e8c-b521-8571cd73f368",
                    "designerReference": [
                        {
                            "_key": "style",
                            "_value": "",
                            "_type": "kv",
                            "_attrDef": "p"
                        },
                        {
                            "_key": "class",
                            "_value": "",
                            "_type": "kv",
                            "_attrDef": "p"
                        },
                        {
                            "_key": "buttonname",
                            "_value": "Cancel",
                            "_type": "a",
                            "_attrDef": "p",
                            "_useAsLabel": true
                        },
                        {
                            "_key": "color",
                            "_value": "",
                            "_type": "kv",
                            "_attrDef": "p"
                        },
                        {
                            "_key": "(click)",
                            "_value": "",
                            "_type": "kv",
                            "_attrDef": "p"
                        },
                        {
                            "_key": "[disabled]",
                            "_value": "",
                            "_type": "kv",
                            "_attrDef": "p"
                        },
                        {
                            "_key": "[disableRipple]",
                            "_value": "",
                            "_type": "kv",
                            "_attrDef": "p"
                        },
                        {
                            "_key": "type",
                            "_value": "",
                            "_type": "kv",
                            "_attrDef": "p"
                        },
                        {
                            "_key": "routerLink",
                            "_value": "",
                            "_type": "kv",
                            "_attrDef": "p"
                        }
                    ]
                }
            }
        }
    }
}
